{
  "code": 200,
  "message": "Operation successful",
  "attendanceStatus": [
    {
      "name": "Dhiman Saha",
      "id": "ESE042DHK",
      "status": "Unavailable",
      "teamList": [
        {
          "id": 6,
          "name": "Meth"
        }
      ]
    },
    {
      "name": "Shouman Barua Shuvo",
      "id": "ESE035DHK",
      "status": "Available",
      "teamList": [
        {
          "id": 6,
          "name": "Andromeda"
        }
      ]
    },
    {
      "name": "Irfanul Karim",
      "id": "ESE008DHK",
      "status": "Unavailable",
      "teamList": [
        {
          "id": 6,
          "name": "Meth"
        }
      ]
    },
    {
      "name": "Arifulllzzaman Tanin  ",
      "id": "ESE027DHK",
      "status": "Unavailable",
      "teamList": [
        {
          "id": 6,
          "name": "Meth"
        }
      ]
    },
    {
      "name": "Md Sajjad hosen Noyon",
      "id": "ESE026DHK",
      "status": "Unavailable",
      "teamList": [
        {
          "id": 6,
          "name": "Meth"
        }
      ]
    },
    {
      "name": "Muhammad Farhadullah Mejbah",
      "id": "ESE040DHK",
      "status": "Unavailable",
      "teamList": [
        {
          "id": 6,
          "name": "Meth"
        }
      ]
    },
    {
      "name": "Mia Hossain",
      "id": "ESE033DHK",
      "status": "Unavailable",
      "teamList": [
        {
          "id": 6,
          "name": "Meth"
        }
      ]
    },
    {
      "name": "Niloy Datta",
      "id": "ELSE028DHK",
      "status": "Unavailable",
      "teamList": [
        {
          "id": 6,
          "name": "Meth"
        }
      ]
    },
    {
      "name": "MD. Junaied Hossain ",
      "id": "ESE038DHK",
      "status": "Unavailable",
      "teamList": [
        {
          "id": 6,
          "name": "Meth"
        }
      ]
    }
  ]
}